colonyzer2/archive.py
colonyzer2/detectlid.py
colonyzer2/functions.py
colonyzer2/independent.py
colonyzer2/independent2.py
colonyzer2/maskfill.pyd
colonyzer2/parameteryzer_script.py
colonyzer2/parametryzer.py
colonyzer2/timecourse.py
colonyzer2/timecourse_fixedpos.py
colonyzer2/timecourse_fixedpos2.py
colonyzer2/tmp.py
colonyzer2/version.py
colonyzer2/__init__.py
Colonyzer2-1.1.13.data/data/data/BottomRightLid.png
Colonyzer2-1.1.13.data/data/data/BottomRightNoLid.png
Colonyzer2-1.1.13.data/data/data/CornerLid.png
Colonyzer2-1.1.13.data/data/data/CornerNoLid.png
Colonyzer2-1.1.13.data/data/data/GreenLabLid.png
Colonyzer2-1.1.13.data/data/data/GreenLabNoLid.png
Colonyzer2-1.1.13.dist-info/DESCRIPTION.rst
Colonyzer2-1.1.13.dist-info/entry_points.txt
Colonyzer2-1.1.13.dist-info/METADATA
Colonyzer2-1.1.13.dist-info/metadata.json
Colonyzer2-1.1.13.dist-info/RECORD
Colonyzer2-1.1.13.dist-info/top_level.txt
Colonyzer2-1.1.13.dist-info/WHEEL
scripts/findAndMerge.py
scripts/independent.py
scripts/independent2.py
scripts/parameteryzer_script.py
scripts/parametryzer.py
scripts/parseAndRun.py
scripts/parseAndRun2.py
scripts/parseAndRun3.py
scripts/timecourse.py
scripts/timecourse_fixedpos.py
scripts/timecourse_fixedpos2.py
scripts/timecourse_fixedpos_1536.py
scripts/__init__.py
