Metadata-Version: 2.0
Name: Colonyzer2
Version: 1.1.13
Summary: Image analysis for microbial cultures growing on solid agar surfaces
Home-page: http://research.ncl.ac.uk/colonyzer/
Author: Conor Lawless
Author-email: conor.lawless@ncl.ac.uk
License: UNKNOWN
Platform: UNKNOWN
Classifier: Development Status :: 3 - Alpha
Classifier: Topic :: Scientific/Engineering :: Image Recognition
Classifier: Intended Audience :: Science/Research
